secrypt/__init__.py
secrypt-2.0.1.dist-info/LICENSE
secrypt-2.0.1.dist-info/METADATA
secrypt-2.0.1.dist-info/WHEEL
secrypt-2.0.1.dist-info/top_level.txt
secrypt-2.0.1.dist-info/RECORD
