Metadata-Version: 2.1
Name: secrypt
Version: 2.0.1
Summary: Simple Crypting library for python
Home-page: https://github.com/rubbieKelvin/secrypt
Author: Rubbie Kelvin
Author-email: rubbiekelvinvoltsman@gmail.com
License: UNKNOWN
Platform: UNKNOWN
Classifier: Programming Language :: Python :: 3
Classifier: License :: OSI Approved :: MIT License
Classifier: Operating System :: OS Independent
